{
  "creds": {
    "noiseKey": {
      "private": {
        "type": "Buffer",
        "data": "2IN+pbkfGSwFZ0NrYTzhJR3lC6I24tyaTSn6B+8vY3U="
      },
      "public": {
        "type": "Buffer",
        "data": "E5ENoay6nHb0LOxF8uhlmpGbgo275kR4TkvRFNBVIXI="
      }
    },
    "signedIdentityKey": {
      "private": {
        "type": "Buffer",
        "data": "mBp2sE/1C8Nn67I7udoGwh1MIyZ2CDMacU8GKW9Ye08="
      },
      "public": {
        "type": "Buffer",
        "data": "QacVatpFc1zeqx5d6/n1Wkz6wH4V8l3KFP92/iYVwWw="
      }
    },
    "signedPreKey": {
      "keyPair": {
        "private": {
          "type": "Buffer",
          "data": "yLt/3XbEJOQLtjXWqORvYXwAa/6+lT/eHxdvoERJt20="
        },
        "public": {
          "type": "Buffer",
          "data": "s5kcySVtt920tK022WyJ0RDAIdXNq2DGv02oqgtWdXM="
        }
      },
      "signature": {
        "type": "Buffer",
        "data": "tQphf0KET7eorG5AzRQijeWCB6j3cLpKKpPJGXKxV4xV4DEmEzFKuvmAD5L+xEUTEsrcdThCF0J8Ay7eHrihgw=="
      },
      "keyId": 1
    },
    "registrationId": 93,
    "advSecretKey": "ZxAZ4ZnFlT55uwKPNH0QSepSv4lJYybcQfElFNeaZDM=",
    "processedHistoryMessages": [
      {
        "key": {
          "remoteJid": "918714291380@s.whatsapp.net",
          "fromMe": true,
          "id": "AEA9755C5834A8BA1FB1EA12D9E66A83"
        },
        "timestamp": 1667815310
      },
      {
        "key": {
          "remoteJid": "918714291380@s.whatsapp.net",
          "fromMe": true,
          "id": "1E7D0590DC61EB6B04CF6BA22203C6B5"
        },
        "timestamp": 1667815310
      }
    ],
    "nextPreKeyId": 31,
    "firstUnuploadedPreKeyId": 31,
    "accountSettings": {
      "unarchiveChats": false
    },
    "account": {
      "details": "CKX17OIGEIivo5sGGAE=",
      "accountSignature": "9a7EKPHnUi5xt4CGTgKcwqLK2m76as3n5DGEHK9JkmFakguCIfUaDIy+pDgp9GXtzqpLoJYCYDPKpLNfDORAAg==",
      "deviceSignature": "pgXsyfRN58e1RGdDTbh4vVy8tD5ITCJ4rsV6wf7u6ivAJAJY1ivWta/0By6dwMUR+CwVjTIT/s5AMiHoe0V7hA=="
    },
    "me": {
      "id": "918714291380:8@s.whatsapp.net",
      "name": "℘⃝♡Lɪᴘꜱʏ🤍"
    },
    "signalIdentities": [
      {
        "identifier": {
          "name": "918714291380:8@s.whatsapp.net",
          "deviceId": 0
        },
        "identifierKey": {
          "type": "Buffer",
          "data": "BWRAtQVBxh6c8/sI4jIE+wFtdnGy8gQtnJ3JUTJtdm4X"
        }
      }
    ],
    "platform": "android",
    "lastAccountSyncTimestamp": 1667815307,
    "myAppStateKeyId": "AAAAAGch"
  },
  "keys": {
    "preKeys": {
      "1": {
        "private": {
          "type": "Buffer",
          "data": "0GXZXS6NgCc58Zge8/YU5AlZia1HEb53g2DGJFfnmmw="
        },
        "public": {
          "type": "Buffer",
          "data": "TglNdM68WKBtIqtaXEHkyg1XO2ByNMTms+Cv94+flm8="
        }
      },
      "2": {
        "private": {
          "type": "Buffer",
          "data": "6Bro0bthe5pQcYZu6L4OVnlxqh7DGzX1hSTfTzcban0="
        },
        "public": {
          "type": "Buffer",
          "data": "UQoT0DcLx6oKty7t/HqxLKsPQ8s0DfXhIAJ/lUZ+Tj0="
        }
      },
      "3": {
        "private": {
          "type": "Buffer",
          "data": "cLcc8rg/n7FF6FyXrNNpbzgAnPgxUiLsIcqZ3DuzbV0="
        },
        "public": {
          "type": "Buffer",
          "data": "jBuzuE3NklgwM42d9Ze4TxGWMzQovGYCguHCrBccDHo="
        }
      },
      "4": {
        "private": {
          "type": "Buffer",
          "data": "gEf1TeRfhyr67BACtNwM6iki9lXAnkTO/mVj0bA7dVk="
        },
        "public": {
          "type": "Buffer",
          "data": "cHDHRh4j3/SKsZ0vddRKuWc8QtGQyEINjqU3N8RyjkA="
        }
      },
      "5": {
        "private": {
          "type": "Buffer",
          "data": "IK4Le6rcpHVA9GMft0GLUfIY4ZVS56pgbriLt3U6YEU="
        },
        "public": {
          "type": "Buffer",
          "data": "mwtOGWULzNdjBceM8S6OHZXYAM1CWY77OFVBB3FddyE="
        }
      },
      "6": {
        "private": {
          "type": "Buffer",
          "data": "iLC5RWI3PKrjnHFwSsSpiclsk0TqmeBO5xX56agVaWs="
        },
        "public": {
          "type": "Buffer",
          "data": "4F+bnazAc8J7nANYvT+V3wXbj19BRstB6crxlcNownc="
        }
      },
      "7": {
        "private": {
          "type": "Buffer",
          "data": "IAUFPHc/L/gKqf2R7IZkrPErf9elkRiWASvf0bdNJnQ="
        },
        "public": {
          "type": "Buffer",
          "data": "osQkYjM56cHy8YXj3GROsZCxsjk7UgwwvKiRtvdwAl0="
        }
      },
      "8": {
        "private": {
          "type": "Buffer",
          "data": "CDql54RqG5kt5HQHyyEXhto/ZyLQ03a9U8IgstNwY2E="
        },
        "public": {
          "type": "Buffer",
          "data": "BBbOf6XqAUbN3vWzdHpp4/oem7IgRQJBVWDagKohK0U="
        }
      },
      "9": {
        "private": {
          "type": "Buffer",
          "data": "8OSrYBKj7BWkSEo9wUNMrOTNCGloVYmzz46O8qQD7kY="
        },
        "public": {
          "type": "Buffer",
          "data": "gEb0t0qazKBcOe+gt135xSmn0C5mu7UrLGSn0cNsH0o="
        }
      },
      "10": {
        "private": {
          "type": "Buffer",
          "data": "iKjTteHMbx6TrC6DTMqP3Fn5Obd56iHVvOI1MIuEZkg="
        },
        "public": {
          "type": "Buffer",
          "data": "WBu6spFdk+977DfTMRAeY+v0V9SW266Dnynpg7alKws="
        }
      },
      "11": {
        "private": {
          "type": "Buffer",
          "data": "+Aj2DIup1dbmX02rLZ0yiaSQiOmT+p+L0zlGOxoOAlQ="
        },
        "public": {
          "type": "Buffer",
          "data": "jhqzP5tDaej5qNRx8nOZjsCHRlf1VLSW/6yU1ODL+RQ="
        }
      },
      "12": {
        "private": {
          "type": "Buffer",
          "data": "WJbSq0/MEw8CFJXgMZbmweEZz4CfSLA/YXiokTTqMVA="
        },
        "public": {
          "type": "Buffer",
          "data": "fx6OFZ5ON0GTSNZuGh39tYEDE1t6GJl95L2D4Nf5ZnQ="
        }
      },
      "13": {
        "private": {
          "type": "Buffer",
          "data": "eMJUibZlw5KcfdEyAV3HuF1Cy5DUtRa0ikJ0I8ouQHM="
        },
        "public": {
          "type": "Buffer",
          "data": "MEGypNaHJS+rJQQvp3T/G0S4jE7lV54d2FaJj/q+RjY="
        }
      },
      "14": {
        "private": {
          "type": "Buffer",
          "data": "EECw2GiVy99NWJVSd7n3deFtW/uQPLzNYjVUMG6hVVg="
        },
        "public": {
          "type": "Buffer",
          "data": "25m8cvu3DRiS+dFXSlHaYKTFy07owFK95pieCB4mFCA="
        }
      },
      "15": {
        "private": {
          "type": "Buffer",
          "data": "GK3GTvXFuHaezXk3ANLNxM32nVqKB/mI0IYCfsvupVQ="
        },
        "public": {
          "type": "Buffer",
          "data": "OOo746ryAIPpbv0DsL7gPkhR9rm91rfCDxdK4GYa4S4="
        }
      },
      "16": {
        "private": {
          "type": "Buffer",
          "data": "wJ9gWQoflvWaH/jiyW1s2ryHidNN3Has2/QmkifaWHs="
        },
        "public": {
          "type": "Buffer",
          "data": "iBuT+AHe+hHARF66ArkHkzR0uCkiN4mPxmt+QNK3BlE="
        }
      },
      "17": {
        "private": {
          "type": "Buffer",
          "data": "eNGk5WNlULdrpDP4+szipFCt2Z24wSILqA8SFC5GDWY="
        },
        "public": {
          "type": "Buffer",
          "data": "czwBWPuag21RNz0LP4mq9RPAbFBGV5GuofxNY8COMis="
        }
      },
      "18": {
        "private": {
          "type": "Buffer",
          "data": "OFym5ETYuS9aQY2ut4qB1KavGfoDMovFvL6k/4b6umk="
        },
        "public": {
          "type": "Buffer",
          "data": "pG/XjLG4n5ZjdmtgLVdAYvjrbuhHga4MJlRMxd5s7h4="
        }
      },
      "19": {
        "private": {
          "type": "Buffer",
          "data": "+GW0Qxyu95Q8COh10PgwAq0joSXehZ8LvD+SUvoWAWg="
        },
        "public": {
          "type": "Buffer",
          "data": "nhHggATRQmfK4kmuC2k+cRrabVMeUBGHlHNr8/Td0yw="
        }
      },
      "20": {
        "private": {
          "type": "Buffer",
          "data": "EJl67cyQz1Hjn5cp4zeBcF0Z7360hqL1ILDYrl5/bX0="
        },
        "public": {
          "type": "Buffer",
          "data": "s+OxKQqxbtf6Yq+WF6F7120eOppuG4j3h9qcyaH1/XI="
        }
      },
      "21": {
        "private": {
          "type": "Buffer",
          "data": "IJV+9Ncc6T+QHLBkFYsHt5h/OX5rNWfbHdu1ZiYHllg="
        },
        "public": {
          "type": "Buffer",
          "data": "K27ZAs00Z5XDF0vs6IBxfESYnYccUxDdpfdu2lW0RQQ="
        }
      },
      "22": {
        "private": {
          "type": "Buffer",
          "data": "6CImk/k2VtXaQ4MFQanxEXrVGXDlmnL/ZhVELSUxmmc="
        },
        "public": {
          "type": "Buffer",
          "data": "Y1D0LIOJW7xPyE/WeBgpbClxEhbDcF89uIdi2OignCE="
        }
      },
      "23": {
        "private": {
          "type": "Buffer",
          "data": "kIX+gt7Mo+lD6uwBmrmJeQkrcDG2ImjTVaEz88VATmo="
        },
        "public": {
          "type": "Buffer",
          "data": "2xKyrX/0mDqHeQjYZYE99egb9ql+pCgkLeNBs+ptfWg="
        }
      },
      "24": {
        "private": {
          "type": "Buffer",
          "data": "kHhnfIHCTGAMXjHynHoYyyzjR2HVNdjR4MZgX8KCW28="
        },
        "public": {
          "type": "Buffer",
          "data": "QCzEXQ5duzYH23KFTMzRqdSiXjViLjGygoAVygW3pDA="
        }
      },
      "25": {
        "private": {
          "type": "Buffer",
          "data": "6IP38hOFFCmugBgxZ5mzreuF3Mk3j1f6+GcGGS+x8WI="
        },
        "public": {
          "type": "Buffer",
          "data": "NEKOo2VmwAeV4dLrwNjYzxcwPOsUsHQK8Fk7AIWT0XQ="
        }
      },
      "26": {
        "private": {
          "type": "Buffer",
          "data": "uIoPAMc9GZ5H7ajlJgjD0Rr8mfDk69WmjWBRlsGwV0s="
        },
        "public": {
          "type": "Buffer",
          "data": "k1FO6hv/0yUNQWKcL1YY6VqjNAbz3qCgJH5DOflT6Wc="
        }
      },
      "27": {
        "private": {
          "type": "Buffer",
          "data": "GCbCJmAtqagcMkNa4FKs8rJpSwqv4W4IM3EV4jmtOHk="
        },
        "public": {
          "type": "Buffer",
          "data": "0FtTVBuBhIbWWICiW5D3mIpXHXaLPvf6uwX7lz1AIDo="
        }
      },
      "28": {
        "private": {
          "type": "Buffer",
          "data": "UJMPyN8I464/VBe0fvzDnumpNClOphIhyHxtYwhIyGk="
        },
        "public": {
          "type": "Buffer",
          "data": "6wP0/TSWp+xxDoBBAqrALGewqfVDTLTpQo4YaejMi0g="
        }
      },
      "29": {
        "private": {
          "type": "Buffer",
          "data": "cBRI5ZOI9sT4RSrRzpApHw0Ji3qzjpztbOAb3FzEw3Y="
        },
        "public": {
          "type": "Buffer",
          "data": "ItjQAUw42oRoQwnAzNMMmHVlzoY3GRhCBXkqhzdc6mg="
        }
      },
      "30": {
        "private": {
          "type": "Buffer",
          "data": "WNo57wGL1W2BH8lKHrIlrsP1RNdj5aOGMkIYu1smO2o="
        },
        "public": {
          "type": "Buffer",
          "data": "Txf707+ax7XVsOoTsh4TUF21/5/x4wqeT2wQGjONemk="
        }
      }
    },
    "sessions": {
      "918714291380.0": {
        "_sessions": {
          "Bc47gcWCizveVCHyPvZKPzW4AuN+Wct9p2ruDY/UNGdh": {
            "registrationId": 1995325330,
            "currentRatchet": {
              "ephemeralKeyPair": {
                "pubKey": "BapI7Pq066m6CNl/vuuQj7rc5nkR7LI5uG2w7+d+Nvkh",
                "privKey": "UIlvqgkaCzW9FRuZ7q7uvh+33hDn2mcvQ+d5tD2CAmw="
              },
              "lastRemoteEphemeralKey": "BYgf28C7bzTLa37NHiulLoJLpIyCzYD4F7q+mJ375Rwz",
              "previousCounter": 0,
              "rootKey": "SZnqtyHbdA1P1H5kVhVlvYCpDykVLNYQieHuvkY+9FQ="
            },
            "indexInfo": {
              "baseKey": "Bc47gcWCizveVCHyPvZKPzW4AuN+Wct9p2ruDY/UNGdh",
              "baseKeyType": 2,
              "closed": -1,
              "used": 1667815308815,
              "created": 1667815308815,
              "remoteIdentityKey": "BWRAtQVBxh6c8/sI4jIE+wFtdnGy8gQtnJ3JUTJtdm4X"
            },
            "_chains": {
              "BYgf28C7bzTLa37NHiulLoJLpIyCzYD4F7q+mJ375Rwz": {
                "chainKey": {
                  "counter": 4,
                  "key": "SCSlxDgZRSzpj+PNF9tvxFPi6o5hRW/jrUBcMBMaH4k="
                },
                "chainType": 2,
                "messageKeys": {}
              },
              "BapI7Pq066m6CNl/vuuQj7rc5nkR7LI5uG2w7+d+Nvkh": {
                "chainKey": {
                  "counter": -1,
                  "key": "9ha9gFbumK5WV5dZ125i655z0OeNIMlOHSvCtY39sKY="
                },
                "chainType": 1,
                "messageKeys": {}
              }
            }
          }
        },
        "version": "v1"
      }
    },
    "appStateSyncKeys": {
      "AAAAAGcm": {
        "keyData": "FEVgKYnRlhrSLlZoKirp9xQVzTX39M0tELo08XhTKEQ=",
        "fingerprint": {
          "rawId": 1817918111,
          "currentIndex": 1,
          "deviceIndexes": [
            0,
            1
          ]
        },
        "timestamp": "0"
      },
      "AAAAAGcn": {
        "keyData": "II/lD/wfXxrzaYovP84RL4m92CgxArzj/3d+3bsjMTc=",
        "fingerprint": {
          "rawId": 1817918111,
          "currentIndex": 2,
          "deviceIndexes": [
            0,
            1
          ]
        },
        "timestamp": "1667814733130"
      },
      "AAAAAGck": {
        "keyData": "jNoTGjqFZ2/k+VxT+FEZcymRy26qqeQgaYJ6kDnv020=",
        "fingerprint": {
          "rawId": 1817918107,
          "currentIndex": 1,
          "deviceIndexes": [
            0
          ]
        },
        "timestamp": "1667745835163"
      },
      "AAAAAGcl": {
        "keyData": "Ev2jHV38BcjLsta0297NbUugIWO9X8OqS9Qlv3Ayh0Q=",
        "fingerprint": {
          "rawId": 1817918108,
          "currentIndex": 1,
          "deviceIndexes": [
            0,
            1
          ]
        },
        "timestamp": "1667747957192"
      },
      "AAAAAGci": {
        "keyData": "xJsizvRFHS1gddiijLO6fQ+Ijph1Em17cI0k+RKiKJE=",
        "fingerprint": {
          "rawId": 1817918104,
          "currentIndex": 3,
          "deviceIndexes": [
            0,
            2
          ]
        },
        "timestamp": "1667743147149"
      },
      "AAAAAGcj": {
        "keyData": "D33kvdknuCc06XVdsGkNVFrGCuD4HBnVUV3QKykG4qQ=",
        "fingerprint": {
          "rawId": 1817918107,
          "currentIndex": 1,
          "deviceIndexes": [
            0,
            1
          ]
        },
        "timestamp": "0"
      },
      "AAAAAGcg": {
        "keyData": "1V3tcmK8ulV4MlR6CQAXmuyi+ZHBZPGpzd2FMv6kCQA=",
        "fingerprint": {
          "rawId": 1817918103,
          "currentIndex": 1,
          "deviceIndexes": [
            0,
            1
          ]
        },
        "timestamp": "0"
      },
      "AAAAAGch": {
        "keyData": "4QW35JVxsTdy/BxwIL8yxkslrprgPb9nqxoM0nuQalQ=",
        "fingerprint": {
          "rawId": 1817918104,
          "currentIndex": 1,
          "deviceIndexes": [
            0,
            1
          ]
        },
        "timestamp": "0"
      }
    },
    "appStateVersions": {
      "critical_unblock_low": {
        "version": 28,
        "hash": {
          "type": "Buffer",
          "data": "k3DBZNQwzDtPJJlK+RgqrJfd021p9AUfP31NCUjtBHYTCz9gUKr2LJqx9cKUtCpdlgKtgEFHB+TVBR5IXuAH110fwHzh1lpcWIT11AvzuSOOuZ+d1bYaoneZX+X9anjZCx8WS1z4HQ0ltPnl7hHZvUXZ7aykA6GEoFafxj1H67U="
        },
        "indexValueMap": {
          "AcO5lRXIf+AmOpd4knBqSJpxEFrw6od/TczfERo0P0U=": {
            "valueMac": {
              "type": "Buffer",
              "data": "6XpDQ3OIrcGy0gY322mQkis+m4bXNpttx1DFLeZkmzY="
            }
          },
          "CcJFCqWfILmNj+QP3smUzlofqctWWrWsBaQUMMItdNM=": {
            "valueMac": {
              "type": "Buffer",
              "data": "HkrQvrtN745HlYwHCXxCat3f5XqqpnMW9BpvjzpU4vI="
            }
          },
          "EY4IKy6U8+A8ZSOKWZfOKJdxChvZK06+0JZkgJzJle4=": {
            "valueMac": {
              "type": "Buffer",
              "data": "GdF1tLQhQNhw+gYtn/+NMPsgpjUVFzc7gOCH7rcPDBA="
            }
          },
          "F2FzjY2bKPu0JeZ0zHyY00HomDe1RKKeyf0PvG8gGJM=": {
            "valueMac": {
              "type": "Buffer",
              "data": "TurXYH46oUZulBuOzqai/YMF1QTmwFX1rNjcm4RhbGg="
            }
          },
          "F5JsyGSpJ5r4y/3svthLmxb5SJ1a15lSF3XjRypffdQ=": {
            "valueMac": {
              "type": "Buffer",
              "data": "5xi/r3rSDVCHd0rRurar1FcH3aWeS4nvBYHbAWnZcOg="
            }
          },
          "G1XYSF4LQ1iQn7GbWxJSStV2Z1lz+/E3QAAW4ywoHP0=": {
            "valueMac": {
              "type": "Buffer",
              "data": "YbvTsbD4GlxEd4/baZbetHXkoMJWd7KMyMgGI1sX8cU="
            }
          },
          "HJGzAQDdYzzYnKXTXsX7iND6T1wDcffYrwWodeuL4bM=": {
            "valueMac": {
              "type": "Buffer",
              "data": "35x62fqUPKV0SNowDCI+vSEjarVWGqwZAepULjX87VI="
            }
          },
          "H3lg5caqpNnIAPdnyCuO72T00xDjOWRWZqPDQaFpxLI=": {
            "valueMac": {
              "type": "Buffer",
              "data": "M4aBgRwF/6nHkqaYSJfAZpagbZonHC4GxhDz8Uj6K4c="
            }
          },
          "KQkeU3mz1z1Jr9jk6X+/3EEWwBEoKyf6l3KlcIga33E=": {
            "valueMac": {
              "type": "Buffer",
              "data": "94gSam/EeLXQjXtQKMc7bn6LtPmkT2ysSAtjOirpbBA="
            }
          },
          "K+ERcE9bKLtrdCYOE2PPrnDlpVHT8kz/OfHGcAM6jl4=": {
            "valueMac": {
              "type": "Buffer",
              "data": "Ei4xqRmaKLY+m82rs8NMMEg5qfEV0sbqywMJTxWZcYM="
            }
          },
          "LgjOdE+W4torGoo0NMOwfQbUNwIaQmPcI/yWKRNWGyw=": {
            "valueMac": {
              "type": "Buffer",
              "data": "jpWtoqtcUzvHePGmFHyk2pIVajCrWWHQ7/+txnvk2EI="
            }
          },
          "Lrq0vvfi7uVFxXlUawzpNY0yG6i81jhi9I1IRhvqM9k=": {
            "valueMac": {
              "type": "Buffer",
              "data": "iGkYJelExqVGiY7ciQ543Qyy6w8D1RE89zLdFV/29gU="
            }
          },
          "MfFks7T6swNcFVai+rBjtsp8bClK1q7QrqzrtO+2Ff8=": {
            "valueMac": {
              "type": "Buffer",
              "data": "FmK+dgm8Hpm+Lh0qgb8/LogvP+PtoG6MBRdt9dg7ihQ="
            }
          },
          "NMy7cbtLlaNWMYYiLkd3aAn003Vmg46qWupXfYof4+E=": {
            "valueMac": {
              "type": "Buffer",
              "data": "JuMAE7tN4Y/klfmVd+Pj70VNYRTk64RzII+2//caAcI="
            }
          },
          "Nn5PNKVoMive2Bak7ePqlXlTl2AM2yUEtu26+wT0tZE=": {
            "valueMac": {
              "type": "Buffer",
              "data": "SB4Uagw7GfMZlBs6ah2a2WhgCmeYHbNyem4hI60bpLc="
            }
          },
          "PJ4n9A9NBO5v99I8WzTht/vhm+4FNZ4aUu0VftlcIag=": {
            "valueMac": {
              "type": "Buffer",
              "data": "EM2S+u9dwYQp12+sAVEX34y6bxbe+Gr8FPEAoEfhiCE="
            }
          },
          "P9YJ2bIBnX49C12k9cwzMgS8sr2pMwyezt14PcwnMY4=": {
            "valueMac": {
              "type": "Buffer",
              "data": "WEAYBP5vFCuTbQE0lGaQYAo30Uj5KPx0WVCbWZmCzlk="
            }
          },
          "Rp7/fpdzS5PhhehdRtqScEGxWETO12TBJe32gUh+fzU=": {
            "valueMac": {
              "type": "Buffer",
              "data": "7hKX+av4CWS0cOvsbuwtsqgqrBvcwDivLmLYsIybO/g="
            }
          },
          "SdvebojIfGBpSb+dQV1VEi4Jv4uzXs0U7UtHl8m2bIM=": {
            "valueMac": {
              "type": "Buffer",
              "data": "JOhe5Af0jeNo/cfo4XxIPmF4recTnVEpeInATaquc4g="
            }
          },
          "TClI4m8abIZ2wthwMhfJ7Ow3seh7stC19cPWnbq2B+g=": {
            "valueMac": {
              "type": "Buffer",
              "data": "aWdaKBH6akXLTsTq60g+i87VqVm07ac5bsv4ZF5isSg="
            }
          },
          "TKq+QkhDRqEMISIXy09wh6QIRqPYp1tvkTCeQnM6jQc=": {
            "valueMac": {
              "type": "Buffer",
              "data": "xv8H7w0P/MuNCne9Y1aX7gXnMAJMlHcKK5/5Wglm360="
            }
          },
          "WHuDoW7dylik6zsQjcd6BMiNUtiOcs+lUY8yGFLl4WI=": {
            "valueMac": {
              "type": "Buffer",
              "data": "ROd9GwjC6A+CU9e0dhWb+rwJ72lImuAAmqcfdL9WDU8="
            }
          },
          "WSUr3P5u/o3DBt6FWEGjlGIW4S+IhedRsuR6sPZ39ps=": {
            "valueMac": {
              "type": "Buffer",
              "data": "fgGOCoZn63DzbkMagZoxYcl4TSgwlgnKMze2QiflPm0="
            }
          },
          "YPt2ASYaVt/P0ybMHwjinhe9PBT87JKO70oaGI1IOCg=": {
            "valueMac": {
              "type": "Buffer",
              "data": "ACgehVtlYDEZSljC2CO+oMJBQ6io/0FDdy5ScBYdi/8="
            }
          },
          "aT/+HLBSVQC77caO7NASBAhOBQmjLyyJXdkN88jXcwg=": {
            "valueMac": {
              "type": "Buffer",
              "data": "IJ3jmiW94SwdK/Nt9I8tjoohtB+pivAVVcPCf5MHhIA="
            }
          },
          "cA982E9/68Wdd9FyR3hN8ge/liUYgrpK8PM4teHdmP0=": {
            "valueMac": {
              "type": "Buffer",
              "data": "iofCBU9BD/e/kv2Fm96U3roWAW+Sz8wnzzdCmwn+Pfs="
            }
          },
          "dLLM5nbniCfIEdnjyxD8wOsDtZFPjrbFWuWGyhP1kJs=": {
            "valueMac": {
              "type": "Buffer",
              "data": "kEyuCBkMr0CxztPdvkN5kAvIgImcLvmqJC1HAVpb44M="
            }
          },
          "dO4mTWxAc96q3WcQ1Uqk5XcGV/xCJqUhFlab18teYOs=": {
            "valueMac": {
              "type": "Buffer",
              "data": "IN28xIkTCf7UQSQsH343bQ+PinMrFaj/OVKgJJs0OYc="
            }
          },
          "ddaehlfpYi+AmWFL5Zy9Ij7vapQu/YQX2QWQ5uXUfvE=": {
            "valueMac": {
              "type": "Buffer",
              "data": "yK6QPtT26tEkHQxyy0qMWVaJ/oS2VZuScQrLPnM0bNY="
            }
          },
          "fExGPw727qNi3A00zh6dBMYqk943s2UOAhyIUxHgKWw=": {
            "valueMac": {
              "type": "Buffer",
              "data": "OsZG00ERI1BAmtrwMMTElSh4mk++wk15a/mOaMll+jk="
            }
          },
          "gNg3hk+XhMsAoOy5W6s0aYjBvnvZuedrdUyOvSjrsZs=": {
            "valueMac": {
              "type": "Buffer",
              "data": "gCY6DpQBVOL60xtqcUQ6jZCZopea5Tphs+NabOpIX0I="
            }
          },
          "gdXhJXqbqyEV5NVR0VO++0AmlqyzHAhwM3wJKuDavqk=": {
            "valueMac": {
              "type": "Buffer",
              "data": "XgXfLsOJ3JqWXKNYk9fZ8MXO0F4dML/EG7YogEeg7sU="
            }
          },
          "iKn+dC/7r10IBDlnyGjNnm/J8A3NgfXnZ2ZJWjsOKpI=": {
            "valueMac": {
              "type": "Buffer",
              "data": "eusR17LsnTrCYmzSyuInMlotm0EnoWYFWPoon0dXGfQ="
            }
          },
          "l4cKKQo9LGl+T3afANgzCuqc+eMPa6SC5G4qO5PJTcQ=": {
            "valueMac": {
              "type": "Buffer",
              "data": "W19Dp5s73cRN4TeDzDgYaMXGfTGmiy6gItO6qiia8MY="
            }
          },
          "mg6RCju3SXeGvjCliiC68BBMJlM0qg9zuYw/ubgRklI=": {
            "valueMac": {
              "type": "Buffer",
              "data": "3wBxH5FxvQWEEyjUVD9+D0TknfD1Vos7yqzMoRp06os="
            }
          },
          "nQRhBPchIvBZFjNdLAjanL+Ovn8Trm5scoQAW0Pj9Ms=": {
            "valueMac": {
              "type": "Buffer",
              "data": "1UPbezOC5WMlICkaPxlcMn/y/cbLoZYX0IkA9UZwQKY="
            }
          },
          "pNZMDziTKoy42Lt3r/rcicTToyhbk4buMuIwVDDLns0=": {
            "valueMac": {
              "type": "Buffer",
              "data": "EtvEM2/gtLouY8iyL0B4r/m99hrmY0Xjq2BWBkdVuZE="
            }
          },
          "pUcDVXBaADJ/vszfLEdl5+kRL0womzml+oJP1dHn2OQ=": {
            "valueMac": {
              "type": "Buffer",
              "data": "0KOx8Vqm/cfiEOUTManonWcnRY8XmD0HDTzbMQyQflE="
            }
          },
          "p5WIwcsWRXSD2HBYAtzzZcvgwn5mV14vPL8T66i81lg=": {
            "valueMac": {
              "type": "Buffer",
              "data": "00vfTSKOTTyimBMmRCLnin5FpSDHd4md56dKvl+1yQI="
            }
          },
          "qSz0vvfRqLIc7Elgs/i3eHzno0JilwU1ZM5mWbVeAPk=": {
            "valueMac": {
              "type": "Buffer",
              "data": "R/8eaAqz394zBUea15qcupse8thpsM7MeiikkmCbp28="
            }
          },
          "rFpMu3fvXfTOQH121sfqPqdZnE/Diq+D4MA9B5Guhy0=": {
            "valueMac": {
              "type": "Buffer",
              "data": "M/yy6iRkkJEbDYFO8TonEIkV4n7acSKLpk8nD2kAVxc="
            }
          },
          "s3aLCK/d8PRjsTNKgjeqYGGr0WjEC/ANGgMAaJzYzic=": {
            "valueMac": {
              "type": "Buffer",
              "data": "p1p3uuNKvaPlNph3PM31MXhTiAOT+U91zOySBEWWoiM="
            }
          },
          "vEkx/T/1QcHZcAMrRXQJoGxj/z0JqHttn+EhgybiCBg=": {
            "valueMac": {
              "type": "Buffer",
              "data": "HvyKUUxgQnYWJpVunif647mqD2yIg2aGwUmY1EcUz0g="
            }
          },
          "vJ5saTMU1XBZGQEe7dxuNE/Uub6nb7b5axv4Tc1fbYQ=": {
            "valueMac": {
              "type": "Buffer",
              "data": "B6332cpTdmR4gMaNlACHFUmlAC59JM4fB16w1tGQ1gI="
            }
          },
          "v9ivKGdSMDiCTM8IMfNs9yt0Kd2WGG3K2/Hx0EAXgNA=": {
            "valueMac": {
              "type": "Buffer",
              "data": "FzgDHGWSuMzb5KbMfXyvMXRd6tLD9+v4l8V9vMKoghI="
            }
          },
          "xGS5tqizR065KKQ+XDDmEGgSQc/m8Z3f4ouywBL+7Y4=": {
            "valueMac": {
              "type": "Buffer",
              "data": "/KCZ/lwXxH+YnC5Wnc7rslOOlHpAQ6iKt9JAVhx0lDQ="
            }
          },
          "yrMqcd+OYT9zJsdBhxvuyHJIqe6Fdlfq4WY9+ufjlsY=": {
            "valueMac": {
              "type": "Buffer",
              "data": "3UBDv2XQs02KjnWNx/mUCquIHjhIPLRezm7X5LB0zYo="
            }
          },
          "zzWOtrPEnxX0rLVdsyQ5Px3czK3sWA8pw7plc19AV7k=": {
            "valueMac": {
              "type": "Buffer",
              "data": "KS5MU7amKCVXODqO625CklYf+KiVTn9GhNP8O6OZO3w="
            }
          },
          "1JmIF6lpEh/eUEnFDFqlw2wVYUVl/c95kM3Ut9ixWSM=": {
            "valueMac": {
              "type": "Buffer",
              "data": "diRs7EtUDgTUZzVu9p23ugEYSVNeQ6dTf0aMayHajH8="
            }
          },
          "3xwlh29soySvd6x0tfp2zMJUzUi9xghlY6KDcYWGiQk=": {
            "valueMac": {
              "type": "Buffer",
              "data": "XmNDc5TVxYh3+Y4lss4izdsPqvLhH7HVN2chSSxSovI="
            }
          },
          "6CU6/c5lrI1JUy9uk2AEUuUZ8sRwM2BMn7kav4rI4GA=": {
            "valueMac": {
              "type": "Buffer",
              "data": "zhfR+A/nIJ+yz+sM2BjmVoqawFigMPLhyx88lboYuak="
            }
          },
          "6cqOPzu9Nqjc4CIdd/CYKjlSHqmxOgMhtblwXY8PYcY=": {
            "valueMac": {
              "type": "Buffer",
              "data": "JWgQenhtH/J5hovfecM39PDhP6kLDa51qtVptOfAvuU="
            }
          },
          "6llkTOdaZj6MrIsTSd0f0aR3sAXHZbuvBqRgvNQ31Rk=": {
            "valueMac": {
              "type": "Buffer",
              "data": "1aiyMst9VY8mwXJgZ/sdYIzHW83UYysJ0bY/W4GKoAA="
            }
          },
          "6sHdNeKSXeY2eL7RPzwmqLYD/pB11kYdRB1H41/IN0k=": {
            "valueMac": {
              "type": "Buffer",
              "data": "QcARsjEs2l4jSPnAPoLlwIxFWwHprpaZkz7HYuQfFdc="
            }
          },
          "7npwqHofEOPjMVuIAx1u7xyofgCMWC2PxbYjgZxFfHY=": {
            "valueMac": {
              "type": "Buffer",
              "data": "M251DqweX74vjdIKdUMZTmAvFs9IMnJWrsRAjLlX86c="
            }
          },
          "8SUym5+We0SZqgXY0siww5D0ptDEDZ3QbKrYxW1LTY0=": {
            "valueMac": {
              "type": "Buffer",
              "data": "vhaQquwz4mHOjf6bYAvXutqxyh/E8KQ0mm5BtMy5RYs="
            }
          },
          "8md90KtefcAACZeQUjRrUiuZIcPewSQrn5Yv6AjJBBM=": {
            "valueMac": {
              "type": "Buffer",
              "data": "sU+7V9WRvMPZ9aDmQhkRobGHUi/SqQVTk4nl/oWfl0s="
            }
          },
          "878EvAAnQdSHuFeIISYt16qbdqUKbzHD/Ax/bpi35q0=": {
            "valueMac": {
              "type": "Buffer",
              "data": "/D18RVlKa/wIWaazS+ryQHVDb8qYuFql17lZP89bxvY="
            }
          },
          "9GnHR2TobNefusqJW3V5c+n2EY8csOuXK1eUDCzD5LI=": {
            "valueMac": {
              "type": "Buffer",
              "data": "vCVQ2R1/jU2lTqz3rhlw4ojQKFRwywL3Fzcq2nA01J8="
            }
          },
          "9rZrrviar2hR9Zmj769UYt94cgPv/n/+lLlShCvhG+I=": {
            "valueMac": {
              "type": "Buffer",
              "data": "rfwl4B+SOTos5DjlSMQLLX62OWZF1b7OT/dD3ulGQvs="
            }
          },
          "+AO+07ta47ggCHJ3ElJUPCrcXeCiH9ENmrNzWjs5kLY=": {
            "valueMac": {
              "type": "Buffer",
              "data": "ogRRm6jHzm1gP72UXYAJ6ZHc9/NtGPNEL1U55vckGt0="
            }
          },
          "+yd7atrj0S9MqBAtE0HpZVlraq7YGTgC2r/FY2hqhVY=": {
            "valueMac": {
              "type": "Buffer",
              "data": "PApoKmSQQ4j76MMZshoj7qr35d6bPKVEmXQd/KR7qRk="
            }
          },
          "/zKDSpzNZ1K+P7IbZR44H/47/9Dj6NhXEN59nim8gqo=": {
            "valueMac": {
              "type": "Buffer",
              "data": "89ds7m0gNm5IGQA+6W3uhgGN8gMi+5Bgycm7bKHShuk="
            }
          },
          "8/2EOQg/v8fsWTF1JabJlM2U7mBs2hn458RpfzzX+P4=": {
            "valueMac": {
              "type": "Buffer",
              "data": "NaiEJNAVb1sPYWAJBLWrSWycHE44pvcHrHLotKBF8Bs="
            }
          },
          "mR8hq+O353AtkYu4drjkrEva6/aqNkCp/OLoERG+5bs=": {
            "valueMac": {
              "type": "Buffer",
              "data": "w7B/+hMAUbxkiW/YrT1EJf5hxz3S6ttLJJMRtX/8Sqg="
            }
          },
          "4Z4xkmhFlKvbw0cThSXVP9+ro6Odo23L+YgQMpfpJ+s=": {
            "valueMac": {
              "type": "Buffer",
              "data": "l29NLiZP9dw1HJZTgZyZY7jHo6Igm5Nj1GRKnp0y9xA="
            }
          },
          "xAQ6qUEbQ4QIH2iX/rL4YWbFGwho6cW1+xlqmgbOQxU=": {
            "valueMac": {
              "type": "Buffer",
              "data": "qb+32H8o+kbgem29WvGi098vOy51zvNt/CGJyXJm93s="
            }
          },
          "81FhaczKtKU/oqoIAEydXSHz6oT9LNkCof0VCu3DvYs=": {
            "valueMac": {
              "type": "Buffer",
              "data": "51ZjVChxzNdz0Yeh4Yw5lyaSwStV9TkIbEpY1YZFQ4E="
            }
          },
          "TmV9Uf5n43nVGqG+o7xuSWfmxM7NhHo7OyICwfBo00g=": {
            "valueMac": {
              "type": "Buffer",
              "data": "c5yYU5VsHzeaJFBBPesCRKM3sABtVi2BWwwktCul5nI="
            }
          },
          "hgpcn7dqx0faozL7iSmKqQNmD+6skwr16MO5Bmw3oUE=": {
            "valueMac": {
              "type": "Buffer",
              "data": "aVo+1Hwn4rxEWeem+/JQfg4KunZQI6Nn2CZqBnzspqA="
            }
          },
          "Cod+1oACxZ5Ns/ms2IHGb+GCHwnu1E3cyiX1lfUwKw4=": {
            "valueMac": {
              "type": "Buffer",
              "data": "e/cdqNpn5J6HdscwrtQAJGsH8Wsq6Oeq4dDvdzGtkd4="
            }
          },
          "O1jRwGxaLwKmgQ/M6a8bbH0OBt2qd4TaLoOSQFT1mKQ=": {
            "valueMac": {
              "type": "Buffer",
              "data": "dzgR7YL5xbtouUv9GfyMZmpQvzV8w7CXJR5nnSZSqkA="
            }
          },
          "4ZuZ/kBwoZw/Qr1jYMJW5DK4DMYHHIpQ/1vNXBy2nCs=": {
            "valueMac": {
              "type": "Buffer",
              "data": "dNtQspDoDiZLaafRbldmEVQ5EgNic7RcoPEbAPN3m88="
            }
          },
          "GS80uKbJwT92SsLxx5xNMapeM7V3iXmaojL0GOX5+nE=": {
            "valueMac": {
              "type": "Buffer",
              "data": "gPBugI2Lhs1WJTynyunqD3WbT2lV4SndkuGRA7dH3xw="
            }
          },
          "hUCw0mH4FWgBUgJawhzkbO2fUY/7FYi6ibzZvkkRF7Q=": {
            "valueMac": {
              "type": "Buffer",
              "data": "zgt2PtgurhCy4zzTKYC1hcWtK1CtXOAWDXYF4tcldos="
            }
          },
          "a+TjQLhal1DHFPkabU0LEqYNJHQ4lrswgQ9recgtdvk=": {
            "valueMac": {
              "type": "Buffer",
              "data": "9c/Alexv3KHl2FdivM+1kxKhooV5qzsPHES0LwgQv5U="
            }
          },
          "pzKUubLwu62PDxg8X/Y3Z7FA8jjTT5H9WHELTWlK/G4=": {
            "valueMac": {
              "type": "Buffer",
              "data": "5Q4iwlT4Krmc29qa9YDX+55eIEw9u93hRznwI9wHn7o="
            }
          },
          "8Nz6m++bEFalPQe6u+rVRVy/ZeZkYMAIWMWUlUH2jpM=": {
            "valueMac": {
              "type": "Buffer",
              "data": "beEcEWM2qKXZlR+xeQWf876ENENI563sKOIkUvDaMKM="
            }
          },
          "lPvFUgC8jJJmgLxnTzYKwEsydtT72K/1dF5n4GALHBU=": {
            "valueMac": {
              "type": "Buffer",
              "data": "z0plCa04vlR+c4kN9gYZ4a+lqzh96PSAE60wm+J5Cs0="
            }
          },
          "j6ZjqWlcnj7obn/+THb4O446oH6+IEipqV6OeV/fc3E=": {
            "valueMac": {
              "type": "Buffer",
              "data": "d5tpPW7OrEc4qRm262L+KRRz71mSDUngSyRD731+3ew="
            }
          },
          "NQ1MCeDQ3hKxftlCvinAKJJpPUTvU10jWQ5VdXrJnOE=": {
            "valueMac": {
              "type": "Buffer",
              "data": "eXfOgywwvSN2ZZRR4ZKyJC1bMfzew2ar3nyy7D4WAiQ="
            }
          },
          "/9twGYenF+iv/XQGCub81sUZBk8+n56FdIft8E/+P3A=": {
            "valueMac": {
              "type": "Buffer",
              "data": "nzjuq0jtcNAb+/e50id0pg4ofVv42t9b73NYD+FW8cg="
            }
          },
          "GuWOnp2BvE4lc2XCkaiZap7wuaBBe0EO3ZuIj4QhUNY=": {
            "valueMac": {
              "type": "Buffer",
              "data": "QTgyJOiTcIIYK5R+eRYC7W7XyorqZXGex8eCaXjRRNU="
            }
          },
          "Ee259c94Sxr9UXpywtcMUl2Fyc606ksm4KpKj91NOSw=": {
            "valueMac": {
              "type": "Buffer",
              "data": "M4uhpsaAohr9ukevGnon4CHxZLyGg91R1/1TG5LQxbA="
            }
          },
          "+Ty9oMJXqPH6/sqTFFB/+df/1sbM5vEMxqvlq754tJc=": {
            "valueMac": {
              "type": "Buffer",
              "data": "+4W3scOhxlZT1jr+VpAGJ0a4vJPqADKJjabgeu3NyTY="
            }
          },
          "uiiZ4hZFW1zHbn3WnS0x9VyFOsvJS2r4KIEcoRCW7gU=": {
            "valueMac": {
              "type": "Buffer",
              "data": "AVoTvsgANqhibXffvzgUIs2fGjj1q0FK0NdvXtSRIZE="
            }
          },
          "XM4dQHwsR9JfWl/hPeZLx7AR1wtEk1/G3UZK4obp9+c=": {
            "valueMac": {
              "type": "Buffer",
              "data": "nbBGqsHxLMOPUA4UP95jfyxNonJtgSdUHaPuaXZISsk="
            }
          },
          "xOlcjjLOu1lTcmRZoWiB2tUaZuMJ0GfZyx5cdvTBVGo=": {
            "valueMac": {
              "type": "Buffer",
              "data": "pFFUGS+LFx89SP2FDeCrchSghuHxwI8yYr3d4a6O/fc="
            }
          },
          "+0+4DOB5dPinuX+zidx2DY0O3HuXxTmqqhvqQ4/Y5Bg=": {
            "valueMac": {
              "type": "Buffer",
              "data": "aqbpSOnB630wu8tc16MTgMShmbgmTBSug4vtTkiUkOs="
            }
          },
          "drggZ5ogYXiiztnbXeSTW6i3m0c1bHy96MjSWMIfoPU=": {
            "valueMac": {
              "type": "Buffer",
              "data": "iGDbGGjL3V5Ks1IIl9x88+uIN9y0EtwsjqtjUyPegk8="
            }
          },
          "8Ppt7dn1gR/wEoK80+unKfhkk3JRMOGk+0RSjpgGF5o=": {
            "valueMac": {
              "type": "Buffer",
              "data": "kfMYL5dqtf3X33ubxMVJIACac1fWrRV86jbSR5pLvYA="
            }
          },
          "DWR/SlTmY06tqgLW3o1Ej31ZPc9JrG2LzIK0n32V9Jo=": {
            "valueMac": {
              "type": "Buffer",
              "data": "A3sIwv8TNUHPTi8PbdfVmz36sAwF2eQZOp8kmWVAZH0="
            }
          },
          "pCgmw4qej4kQ/ZG5RMwT06zQVxm/3H+hJ3fYSM5T4iw=": {
            "valueMac": {
              "type": "Buffer",
              "data": "QOj4BLd6/XTB8fsFfBJQ6DrNWyR0Sbj87alLHn+ttnE="
            }
          },
          "wmq/vcW0DCEH9xszfdz5LJB0wloJ2o//ss242jLTRBM=": {
            "valueMac": {
              "type": "Buffer",
              "data": "5rouZDtwwz/LaK0OLnX3/CIo+rETSsjyFiI8tphGC6g="
            }
          },
          "bztQyQpbeBs8sVBxAbkH2Nvgd+iqGBgja4ay4GxcsvU=": {
            "valueMac": {
              "type": "Buffer",
              "data": "8XDaEqgeESGvua2CbcN0cMszfLFYOnHsU3uH/E0n/HY="
            }
          },
          "VAzb0BAZIrU4rDp21lw6a6O+WGb50v/3ibmopymS724=": {
            "valueMac": {
              "type": "Buffer",
              "data": "hyl7zTOUYwQ8OtGcBUmqP76pBRFKaydsevh6XZmD/6o="
            }
          },
          "/YCaK8YBcvkxe8utP2QIn9lKBbYUYfwBtW2sS4xKA30=": {
            "valueMac": {
              "type": "Buffer",
              "data": "kITvqPcH5qI3bEIBFCHMCWnEwjRiJzywory3D/Lt5bo="
            }
          },
          "bAu0Y582IAjApgNn4eOcw2ZXVWdRkRfYm9ye2UD7DkM=": {
            "valueMac": {
              "type": "Buffer",
              "data": "Xf+Mc8QNeqiAisKhd+0fRgB8k7eEgTgxEibWJZ8A1/c="
            }
          },
          "QWPTdDTwq44ERk7qiRsr+3x7bVa4Z9M3aY3rFUpurdM=": {
            "valueMac": {
              "type": "Buffer",
              "data": "4zvku01HpaltxjPraHLesrwJau3BLqZUeCuLeI75VU0="
            }
          },
          "kSl1ePtR/zDREtPtgrV4sM5pkAKFBWRVcbwQnIPwKBE=": {
            "valueMac": {
              "type": "Buffer",
              "data": "oyuO7gAf52m0DV9uxlzYBPEUC6WT7uOsv44eH6/Bxb0="
            }
          },
          "694gHZYrX5TkXHCcwR9GfZekL1weSQYZXBiLk+hssY8=": {
            "valueMac": {
              "type": "Buffer",
              "data": "AYt6SWQN5FguPDyb5+RZfVr06/vQyqw9iHiPqwJFzHQ="
            }
          },
          "xNbtiuGJs2d4DA2Q7DUUNthkmWvxOC+DnTCWn6t7bH0=": {
            "valueMac": {
              "type": "Buffer",
              "data": "UNPSTbP4KZeGkmtmSPWg5yqa/EXS09hTvWiGOJNYAN8="
            }
          },
          "s41TFUxIiNddhJawXhN3qNNXLuvvqjoG9H1zsDYfDYg=": {
            "valueMac": {
              "type": "Buffer",
              "data": "pbcUIMbQP3mkrhAqci2bgrlmL/FIVPFgAKtk6RYyNo4="
            }
          },
          "l5fThwMWLh6OG1fWq5+IxfYriD9ReAmlnEV50txMicc=": {
            "valueMac": {
              "type": "Buffer",
              "data": "JjV9dPUXD+SuT2VdakpZkkXFMbcwI87/y3uOB1cd1gE="
            }
          },
          "QeNitGk+fle0jVVNpAygXE1vPFUNih5VXaUUKDbNUMs=": {
            "valueMac": {
              "type": "Buffer",
              "data": "p44HF/AlmUisW/mYs7CQfhGmtWBx90jErfexPTd/tvo="
            }
          },
          "7SFOEF2v8DmCScSzeg38/b6+6fj69c9Ld7HQGoUhWGg=": {
            "valueMac": {
              "type": "Buffer",
              "data": "XlouAQLKg3RvLlOenpCF8efzEuCgtylNEFCKIcJ072Q="
            }
          },
          "B8GYBLr8Wyus+mZR9VyQAF9PlFa62Rv1ex+DT8rDKhY=": {
            "valueMac": {
              "type": "Buffer",
              "data": "HsoZNaAPPhkoUTwJgjVTXyjCSd/rTEtYRqWSJ1qNKVY="
            }
          },
          "5gNPaSwDk7WcBur8zhbeidM42LXro41jjYCUPQHlFdQ=": {
            "valueMac": {
              "type": "Buffer",
              "data": "fuRDuESOU6VzLcOh+611wzyBaIvfXMcQtcIn1witwF4="
            }
          },
          "GYju+uWlthV7MMB0KIbFWvHfAtYvZDrdH4M8C/J4cWA=": {
            "valueMac": {
              "type": "Buffer",
              "data": "ZMsx55/DRM+oAPBL/vb91Ai7avuxHuKrlcEzz8/P3ao="
            }
          },
          "Xb0+zz2L5PCVT5q8OzlsaE4lVUNglK4r6f8k8fxZiqQ=": {
            "valueMac": {
              "type": "Buffer",
              "data": "DlyqkD2DQYy1Uo9xASj+1/4qNeRGrr+hiBP7IVEbORo="
            }
          },
          "nUjaqTuFfsIN5VbGqbbwpkqnaDaPcpTAqCJnUVhRBas=": {
            "valueMac": {
              "type": "Buffer",
              "data": "4Lri262ZEJcUMti21kC/mBbc3JraXQyCvxN3gbNsvx4="
            }
          },
          "VusmvSPZukr8Ck0at7Kf657JExRTO2uG0uH/mxCUtD8=": {
            "valueMac": {
              "type": "Buffer",
              "data": "h7htu/YD8qyFteKvqGOzHOxqhZSjNAWqLhlQDr7ucQ0="
            }
          },
          "QtsythtsqQhT9ecFoEFanEZdrSVyLvSE5/BWqksqW+g=": {
            "valueMac": {
              "type": "Buffer",
              "data": "Ah1P+Wld6f0f0/YQ2qHizm/mKDi+AMvONH/gymCyuyE="
            }
          },
          "5MBNGxaKt554f9EyIJM29HWZdIuN4Xshq68ucyPzZHs=": {
            "valueMac": {
              "type": "Buffer",
              "data": "De2nYhxtsMrlRNidL27glpxDvFq62rw1kYycLXG6O7U="
            }
          },
          "Zy+jdD0BWyVw8D4wy41JlK0mw8aPft31g4qv6ViUyNk=": {
            "valueMac": {
              "type": "Buffer",
              "data": "Bzhhs60xjrrM5hXoBzyMYlq/dy12rAWLUIErDR45R80="
            }
          },
          "+wGPrXU52qIHb4YMVo5uVKi4x2EUVHXc17/md9ZhnUM=": {
            "valueMac": {
              "type": "Buffer",
              "data": "2MWTCQVaGMOKCmOJCbDFcQlTZ/9lyLs1nz6eksds+jc="
            }
          },
          "BST5CCXc13TISbTB/o4HCSoFu0mJQ21czEGdsVdrryU=": {
            "valueMac": {
              "type": "Buffer",
              "data": "WTN+Emzc3ktc5hn60Mzbeaspb0P5aZKGQOw7piCnMfA="
            }
          },
          "kVIiDFSKw7dJxXc0v4Tx+RwAvbk84MXFBWFL9irox24=": {
            "valueMac": {
              "type": "Buffer",
              "data": "XGXCN0w5Ijf9FrQcFEfVMrhWbWPOESfR6llWS4EH7Zk="
            }
          },
          "SGpwCPgymvaFDtDZ1rGzCauu10mvDoVdDfy5dy/T+yk=": {
            "valueMac": {
              "type": "Buffer",
              "data": "No54vZStVh3sqJ6XWL5BHGsihDm7pm9I3iWwdJhluZw="
            }
          },
          "sD3eZYeQFAStAep/1KHplUv2Ac8haJaViMcEuT8Jgtk=": {
            "valueMac": {
              "type": "Buffer",
              "data": "fD+ujsMc1tjnu7syqTTxs3DqHIJHOo+1rw0yz4HsfDo="
            }
          },
          "akNED6xhhV78GyVaQEkvnQkLmekrjzuuRn+hTcTaf9k=": {
            "valueMac": {
              "type": "Buffer",
              "data": "inFkSB+cgFWIxgNrXrtb80EjGxaHJLZ8AzuW1ETqytQ="
            }
          },
          "L9AFAGEQNKrA2UN6uW/tRa3vQG1O9+IJ4XuJEokbL28=": {
            "valueMac": {
              "type": "Buffer",
              "data": "Q98t8WeOGGfLCQrdGjcgRKe0ooh32PHvK4PKzFHOIj4="
            }
          },
          "sCnuWZ6cI6jkmLxlzLJyFV7wV9o8P3cHsx1P3iPC/gE=": {
            "valueMac": {
              "type": "Buffer",
              "data": "3IgGUcusy/f3nKp/4EOG/sUB73BusrKzeIqlPTVBq54="
            }
          },
          "AZUfdtLRnalhNnUFmD/Xp4DhMbLfwUnbnaFfW3/VjEE=": {
            "valueMac": {
              "type": "Buffer",
              "data": "G+0QkYWN3aoUVwFfLUgIcDI7Zt0en4KsgucUQbZEIpw="
            }
          },
          "A4F8WUGcDVteCQ84iP/W1iZCBC7vZXY6T/DKz10ul0A=": {
            "valueMac": {
              "type": "Buffer",
              "data": "VMmOhXAFZx+m30fjWSF8y6yre3O0100R7PLoh9V5DN0="
            }
          },
          "P2GBXO+wnpPcAdBf2MxIZyQEwa0IsZ0V1gv5Se14iNs=": {
            "valueMac": {
              "type": "Buffer",
              "data": "m9ZBQk9Pq3weBcPm4H1ijvXZ8/iiaOEsFEJ7VoBJHic="
            }
          },
          "/rXYVzWMrfaRo/QVSLxsvGwaeSUPkSEdDcDMdk29Dbo=": {
            "valueMac": {
              "type": "Buffer",
              "data": "FlsgnshvabYli8PzbQZTj/YsQ/ixM/Gxwj93lvcnD08="
            }
          },
          "6aftXlbrfv9NEMgOMq59KhfK1gLm8zwGvnaGXtI0BHM=": {
            "valueMac": {
              "type": "Buffer",
              "data": "MWgPis2vCsU4VNjYK+3R2Wv1CqjfsguhUvVMS46sOd0="
            }
          },
          "Sag4hoc1KAuK1/ewNjd/DSrtkrup++Vi4MOFgUVbu40=": {
            "valueMac": {
              "type": "Buffer",
              "data": "p9REx/KGpNxsCI/EnqXQMGln20wPIb5QD9RS87c3fec="
            }
          },
          "gYAnOqD/aUX2gtLVe6ObEWnWg1YsntZyvWB3HCtZdgk=": {
            "valueMac": {
              "type": "Buffer",
              "data": "75HszmR8bJWQFcB6I9B9XZNWvZ+n+aTFbw2QqVwG0kY="
            }
          },
          "LyxZI9tRXNe+gBZGGPX7OG09+KVukdjKHYeDlnv24b4=": {
            "valueMac": {
              "type": "Buffer",
              "data": "NUoSZDkb5ZIERLoP4MukFXGzFb6QcsT/xiYzdWW8k9o="
            }
          },
          "5f8S9myUUZ2ycZUBPyDZss0suqELEJiyA5Tk0dduK34=": {
            "valueMac": {
              "type": "Buffer",
              "data": "f66UdROonbPlF0qV1DroZss/+O/fm08VPLOkTiu7ZP0="
            }
          },
          "VCtGqJE9NTJmYY4TTv9p74Cfikjtl7GePdw80D0Uw7w=": {
            "valueMac": {
              "type": "Buffer",
              "data": "qsU1i5L82bm61dvg6/J1gAmpATH4yx4iXrQA2P7ecK0="
            }
          },
          "/cMMQxs6ZPpqmBJXLHrLuchaXFacnKbA9+4oPkRqLI4=": {
            "valueMac": {
              "type": "Buffer",
              "data": "z7/OieUdHI7JFHxchtu85NSr957Z3svgFxpl8ZGV0eQ="
            }
          },
          "pkr74ZniJYsQeOfFfwWkOykscVpwgyQ9lRVTC8ZxDqU=": {
            "valueMac": {
              "type": "Buffer",
              "data": "zctCbZTY6eK9A0UuI7E/DyNOtIEBoaBmG88viN/gQyA="
            }
          },
          "uUrVd/C3r8ooGzv4+5Uvy3f9j6geLx80T67C7zUgzDQ=": {
            "valueMac": {
              "type": "Buffer",
              "data": "NjzrcffVGRYTQQDPnUOy3/iex0ONNFsQe/nyuTdsNJc="
            }
          },
          "9diUFI0FVT1tJLNYOlyKA3mjFBOlVsxSlDLIlsTtmws=": {
            "valueMac": {
              "type": "Buffer",
              "data": "LT7cpJzvPh5Y4WfS38mBAAJEPgW+lz6i5Cklr/+8C3c="
            }
          },
          "KALzTOvUJTE0+Dw0Oaqus+Zv/MvveNLxJBmv5YtKOyo=": {
            "valueMac": {
              "type": "Buffer",
              "data": "BC4mR40WkyqHO1VDY+BfRZUiGCWYAFS37U11AvZ//XU="
            }
          },
          "WnDN483lslzrWAa4Y6SfIAPGfS8DHH7bVnZxz5d0N4Y=": {
            "valueMac": {
              "type": "Buffer",
              "data": "pKKS1q1ATg1eaapPGlbm0MBCqu/t+NlL1j72jLIhPac="
            }
          },
          "eqdA16qlz3gv78LcoNqOYO+aE9zfqM1HJsXjP7Abp2A=": {
            "valueMac": {
              "type": "Buffer",
              "data": "XMpo0varNkY+UEim8k7GPxY8n6ZkUyQo0aYBOjUjPSY="
            }
          },
          "HKFmlpjrrsbwueCYO3TOMn0ovoToLpp24ln/gl6S968=": {
            "valueMac": {
              "type": "Buffer",
              "data": "nTur/P2N0TDwVEc21bKJECAFUKPXOvyX9VpmSTZ/XuQ="
            }
          },
          "2MD5Ic52YhvoxcVxdFlJTOm0chZFPsTnO//xCywpPck=": {
            "valueMac": {
              "type": "Buffer",
              "data": "CqYYgfmxd+GXUO5DKJp/z89j8O5NtWyuKmyh07UOUBk="
            }
          },
          "Trm87JZxBLkS3/s/1/CvJlitN5Ap8Etq9GzoKbl4l9g=": {
            "valueMac": {
              "type": "Buffer",
              "data": "mr7EwQkXP69svy7QwFuYxNFyQvTkCARKoHnvF85OMXE="
            }
          },
          "hgRx9jPqJuRA5Uydh9wZMXOCcvibsyCOzD1OhbpCmx0=": {
            "valueMac": {
              "type": "Buffer",
              "data": "20DXZox1bULPIcFo14FVEHBYY5Ka/oFTqS7GgMtTOIE="
            }
          },
          "zqqEtx4TPHaq2geS8am5ktI6qzvt/inH4F+CRRmPUpY=": {
            "valueMac": {
              "type": "Buffer",
              "data": "ODItPOKp7tWEDbchUkME5b91uejYnaBD8xhsjOmiGHY="
            }
          },
          "Vv0LqOp7iUbBzeJTXV0TmIoY/BpcQg8OdArTRZKVMR8=": {
            "valueMac": {
              "type": "Buffer",
              "data": "gKwBri3sKnfH6o8HJtfSU0yb81hDkC8WBeK9SHjU9as="
            }
          },
          "St8tBCZijt5vpwXuonzpZSNEcwsTnrBltUf6bhLD43I=": {
            "valueMac": {
              "type": "Buffer",
              "data": "IywWsPwZCf7/OJqhk2T6QhyMrRk7650nExg2w5DAIKU="
            }
          }
        }
      },
      "regular_low": {
        "version": 9,
        "hash": {
          "type": "Buffer",
          "data": "/ZcZ+XHLCkT7uqs3jcPLvtP8XhhYHJI7rdOiJoREq8aOuZqg9iXWlmn/0H0koHKakxLnUdcbIdMQBVqnnYheHwxiZkObVbqJtbO5rnVbCMYfiDKzRhWH1BYWNazEyEyoUMZm3fqhXUf57+MclgvxW+qD0efJxo7Vp1Nxy4W1DdM="
        },
        "indexValueMap": {
          "KM4YbsppT3ygK8dduhL8GSDkKit49mUragQuhRvwgbI=": {
            "valueMac": {
              "type": "Buffer",
              "data": "ceNcR/upWaiShW+/4TL7oXyV+RMAqGQsrZnRZWSBwFk="
            }
          },
          "zoHu+LD17+WMOaG6ukNk6rJf0DTMb6i6P0oyIMZ9JTg=": {
            "valueMac": {
              "type": "Buffer",
              "data": "U9gq45hSX71CWs9W2JW8ARM/0bBeDy6yNFNV7AqvkYU="
            }
          },
          "Hu/Rh8apUv3LoSeVYeOVBSO047l9gawQYmAVdaHnK8g=": {
            "valueMac": {
              "type": "Buffer",
              "data": "sGhmVZzHH7S4Hmb3+d3FbuDKytNOIMxzMp3lT/ZgKe0="
            }
          },
          "9rwMLV+36xIZmIr8SF0iBelO9Xdj2FfGyU0tlWiouIs=": {
            "valueMac": {
              "type": "Buffer",
              "data": "B1/unFHx2qWAOSNEIu9ZZgyaHyihV4532WnDjzCdqXk="
            }
          }
        }
      },
      "critical_block": {
        "version": 9,
        "hash": {
          "type": "Buffer",
          "data": "2w0KU0BkPCetgn/Hc4Rnp5FU58pLnPNBf0HEBYuFkm5l3RAt7eFVJ9nGJiPtjz17ruCYVeU899axwG+CdukN9rNA+K/TbCbQtQon9YGc72GcdsdAvkOn7G8r7EE33dBtAOR+J/8p1LXvIVuFHxCPV7Cmzunw/RiWMJrpofly5tU="
        },
        "indexValueMap": {
          "pUlOdWvDOzmfd+Ng12K5JCGyRjLDVCop0qS+IhlJces=": {
            "valueMac": {
              "type": "Buffer",
              "data": "7QG8p14a3C/orC/Hi6jLCg9BZ37XpreUGiY6PVefAhc="
            }
          },
          "0cJKJQ8Rv8CLu9rzovTJ/FDbfVaWsD+xtbtQjoiJP4U=": {
            "valueMac": {
              "type": "Buffer",
              "data": "9x7/+bTsNXLHPlUSMGso6jP57O/ZESsgqbfhK57MLyA="
            }
          },
          "ZJHUBN6X/VgepnNhe1VxhpW6o88RCiYPqZgQs2boDJs=": {
            "valueMac": {
              "type": "Buffer",
              "data": "krSaVeJ6e1fUmGE6OM0rca66y/grQNahF/ppJemX6AU="
            }
          }
        }
      },
      "regular_high": {
        "version": 8,
        "hash": {
          "type": "Buffer",
          "data": "PwpTBOLrtstvzhbr4IaE5mZStdmhbOQJVajGIwPxTyoZ/mzFwLz0yTRv8mtCrzrfl9hrU7Or4A6ggTnwDaDq/GTAZvstHCLft5nx5MYfvfvEel+ILFYDIeJw/iZCpskrIErNIbd7iu+cWjhIAFRPFwmydtEUZlJAFNV1+u8ryHY="
        },
        "indexValueMap": {
          "JHhyI0Wu2rNruJ2kr9ZOlf64hw0REUixb5QIMmI4ppM=": {
            "valueMac": {
              "type": "Buffer",
              "data": "+OS2SRH9aAhgAAhlZKqK6nV1PTI4FQRrDQFkuWbCWB4="
            }
          },
          "ebjY2+xG131/eyI7VE8hLMHPVvUHT7OJtd84UItwT/w=": {
            "valueMac": {
              "type": "Buffer",
              "data": "VqmogfvYVK34CYSp1X+Wvy9pFxCWlGE2zXRyGXgSP/U="
            }
          }
        }
      },
      "regular": {
        "version": 8,
        "hash": {
          "type": "Buffer",
          "data": "BdNKmGugLBDdNXVqrXTXMJYwMDu5YSA2MhmtUu5PQFZwEFa1lblT1TGqLPOCsHDKVPrujCZ5uxaYY1PQpaq8Ce+yt3NGpXyJvtU6MfoKH9M0LWDY4jIfEK/mw5jmDwfdW4CB9b/RDrqTkFyy4BOaSdiKPOSyqktlYJuQ45XuzYg="
        },
        "indexValueMap": {
          "OrGKwijZDr7je2AW+0TvOs2rQWX6mKMv70Z6bTVIqgk=": {
            "valueMac": {
              "type": "Buffer",
              "data": "F2ddLG85kzX4jw4NWEc2qei0JY+Vg6LGYAiGSFMMXfM="
            }
          },
          "t0yQsqtVu+83cg1wgE5ET1Oa1Npormt86y9JMMoOPt4=": {
            "valueMac": {
              "type": "Buffer",
              "data": "qtsHz92STZ7dO6nG/04a4HBgqZylNlTRtEsfWjn1a2I="
            }
          }
        }
      }
    }
  }
}